{
  "matrix_version": "1.1",
  "created_date": "2026-06-21",
  "project": "E-Commerce Conversion Intelligence Platform",
  "total_rows": 204,
  "areas": {
    "ANOM": 10,
    "ARCH": 10,
    "AUDIT": 16,
    "BATCH": 10,
    "EXEC": 12,
    "FCST": 12,
    "GOV": 12,
    "JOURNEY": 10,
    "KNN": 10,
    "MODEL": 14,
    "MON": 14,
    "QA": 17,
    "SEG": 12,
    "SHARED": 18,
    "UX": 15,
    "XAI": 12
  },
  "statuses": {
    "CONDITIONAL": 25,
    "EXCLUDED": 2,
    "VERIFIED": 177
  },
  "required_categories": [
    "EXEC",
    "SEG",
    "KNN",
    "BATCH",
    "MODEL",
    "XAI",
    "FCST",
    "JOURNEY",
    "ANOM",
    "MON",
    "ARCH"
  ],
  "theme_rule": "Preserve and enhance the current Streamlit theme; do not redesign from scratch.",
  "existing_visual_rule": "Audit every existing visual as KEEP, ENHANCE, REPLACE, MOVE, or RETIRE before coding.",
  "implementation_gate": "After remediation, final QA, approval, and remediation merge.",
  "files": [
    "docs/streamlit/STREAMLIT_VISUAL_ENHANCEMENT_COVERAGE_MATRIX.md",
    "docs/streamlit/STREAMLIT_VISUAL_ENHANCEMENT_COVERAGE_MATRIX.csv",
    "docs/streamlit/STREAMLIT_VISUAL_ENHANCEMENT_HANDOFF.md"
  ],
  "last_reconciled_date": "2026-06-30",
  "active_branch": "feat/streamlit-visual-intelligence-enhancement",
  "package_checkpoints": {
    "package_01": {
      "state": "committed_and_pushed",
      "commit": "82c3f66",
      "evidence_file": "docs/streamlit/PACKAGE_01_MATRIX_EVIDENCE.csv"
    },
    "package_02": {
      "state": "committed_and_pushed",
      "commit": "a60dcbd",
      "automated_result": "37 passed in 4.94s at final isolated verification",
      "visual_qa_date": "2026-06-30",
      "verified_rows": 10,
      "excluded_rows": 2,
      "evidence_file": "docs/streamlit/PACKAGE_02_MATRIX_EVIDENCE.csv"
    },
    "package_03": {
      "state": "verified_with_documented_qa_exception",
      "baseline_commit": "a60dcbd",
      "verified_audit_rows": 13,
      "inventory_components": 175,
      "quarantine_items": 33,
      "browser_screenshots_produced": 0,
      "browser_capture_status": "waived_after_environment_incompatibility",
      "capture_exception_file": "docs/streamlit/PACKAGE_03_CAPTURE_EXCEPTION.md",
      "final_result": "docs/streamlit/PACKAGE_03_FINAL_RECONCILIATION.md"
    },
    "package_04": {
      "state": "verified_by_master_closure",
      "title": "Batch Scoring and Campaign Intelligence",
      "closure_evidence": "docs/streamlit/CLOSURE_SPRINT_FINAL_RECONCILIATION.md"
    },
    "package_05": {
      "state": "verified_by_master_closure",
      "title": "Model Decision, KNN and Explainability Intelligence",
      "closure_evidence": "docs/streamlit/CLOSURE_SPRINT_FINAL_RECONCILIATION.md"
    },
    "package_06": {
      "state": "verified_by_master_closure",
      "title": "Segmentation and Customer Journey Intelligence",
      "closure_evidence": "docs/streamlit/CLOSURE_SPRINT_FINAL_RECONCILIATION.md"
    },
    "package_07": {
      "state": "verified_by_master_closure",
      "title": "Forecast, Anomaly and Monitoring Intelligence",
      "closure_evidence": "docs/streamlit/CLOSURE_SPRINT_FINAL_RECONCILIATION.md"
    },
    "package_08": {
      "state": "verified_by_master_closure",
      "title": "Architecture and Governance Intelligence",
      "closure_evidence": "docs/streamlit/CLOSURE_SPRINT_FINAL_RECONCILIATION.md"
    },
    "package_09": {
      "state": "repository_ready_for_streamlit_community_cloud",
      "title": "Final QA, Merge and Streamlit Community Cloud Readiness",
      "closure_evidence": "docs/streamlit/CLOSURE_SPRINT_FINAL_RECONCILIATION.md",
      "deployment_platform": "streamlit_community_cloud",
      "deployment_branch": "main",
      "entrypoint": "app/Executive_Overview.py",
      "python_version": "3.10",
      "dependency_file": "app/requirements.txt",
      "secrets_required": false,
      "public_url": "pending_project_owner_authorization"
    }
  },
  "next_controlled_action": "Project owner authorizes GitHub in Streamlit Community Cloud and deploys branch main with entrypoint app/Executive_Overview.py using Python 3.10.",
  "closure_state": "IMPLEMENTATION_COMPLETE_AWAITING_STREAMLIT_COMMUNITY_CLOUD_AUTHORIZATION"
}
